Workbook

Sheet Start here
A1: PM DataLab: Excel practice workbook
A2: Fictional company "Prairie Logistics". All names and figures are invented for practice.
A4: How to use this workbook
A5: 1. Read an exercise on the Exercises sheet.
A6: 2. Go to the sheet and cell it names. Yellow cells are where your formulas go.
A7: 3. Where an exercise says "fill down", write the formula in the first row and copy it down to the last yellow row.
A8: 4. Compare with the Answers sheet, or the green cells on "Projects (solved)" and "Tasks (solved)".
A10: Legend
A11: Yellow cell = your input (formula goes here)
A12: Green cell = model answer (formula)
A14: Online version with instant checking: https://pmport.ca/pm-datalab/excel

Sheet Projects
A1: Project ID | B1: Project | C1: Department | D1: Manager ID | E1: Status | F1: Priority | G1: Budget (BAC) | H1: Actual Cost (AC) | I1: % Complete | J1: Planned % | L1: EV | M1: PV | N1: CV | O1: CPI | P1: SPI | Q1: RAG | R1: Budget check | S1: Manager
A2: P01 | B2: CRM Upgrade | C2: IT | D2: R01 | E2: In Progress | F2: High | G2: 250000 | H2: 182000 | I2: 0.68 | J2: 0.75
A3: P02 | B3: Data Warehouse Migration | C3: IT | D3: R02 | E3: In Progress | F3: High | G3: 480000 | H3: 265000 | I3: 0.52 | J3: 0.55
A4: P03 | B4: HR Self-Service Portal | C4: HR | D4: R03 | E4: Completed | F4: Medium | G4: 120000 | H4: 128500 | I4: 1 | J4: 1
A5: P04 | B5: Warehouse Automation | C5: Operations | D5: R02 | E5: In Progress | F5: High | G5: 900000 | H5: 410000 | I5: 0.4 | J5: 0.48
A6: P05 | B6: Customer Feedback Analytics | C6: Marketing | D6: R04 | E6: In Progress | F6: Medium | G6: 95000 | H6: 61000 | I6: 0.7 | J6: 0.65
A7: P06 | B7: Office Relocation | C7: Facilities | D7: R05 | E7: At Risk | F7: Medium | G7: 210000 | H7: 150000 | I7: 0.55 | J7: 0.7
A8: P07 | B8: Cybersecurity Training | C8: IT | D8: R01 | E8: Not Started | F8: Low | G8: 60000 | H8: 0 | I8: 0 | J8: 0.1
A9: P08 | B9: Budget Planning Tool | C9: Finance | D9: R04 | E9: Completed | F9: Low | G9: 75000 | H9: 71200 | I9: 1 | J9: 1
A11: Total
A13: In-progress projects
A14: High-priority budget
A15: Portfolio CPI
A16: Blocked tasks
A17: P04 planned hours
A18: P01 tasks done
A19: Largest project

Sheet Tasks
A1: Task ID | B1: Project ID | C1: Task | D1: Phase | E1: Planned Hours | F1: Actual Hours | G1: Status | H1: Owner ID | I1: Hours variance % | J1: Labour cost
A2: T01 | B2: P01 | C2: Gather CRM requirements | D2: Planning | E2: 120 | F2: 135 | G2: Done | H2: R06
A3: T02 | B3: P01 | C3: Configure CRM modules | D3: Execution | E3: 400 | F3: 380 | G3: Done | H3: R08
A4: T03 | B4: P01 | C4: Migrate customer data | D4: Execution | E4: 240 | F4: 210 | G4: In Progress | H4: R07
A5: T04 | B5: P01 | C5: User acceptance testing | D5: Testing | E5: 160 | F5: 60 | G5: In Progress | H5: R09
A6: T05 | B6: P01 | C6: Train sales team | D6: Closing | E6: 80 | F6: 0 | G6: Not Started | H6: R01
A7: T06 | B7: P02 | C7: Assess source systems | D7: Planning | E7: 150 | F7: 170 | G7: Done | H7: R06
A8: T07 | B8: P02 | C8: Design warehouse model | D8: Planning | E8: 200 | F8: 230 | G8: Done | H8: R07
A9: T08 | B9: P02 | C9: Build ETL pipelines | D9: Execution | E9: 600 | F9: 340 | G9: In Progress | H9: R07
A10: T09 | B10: P02 | C10: Build Power BI reports | D10: Execution | E10: 300 | F10: 40 | G10: In Progress | H10: R10
A11: T10 | B11: P02 | C11: Data validation | D11: Testing | E11: 180 | F11: 0 | G11: Not Started | H11: R09
A12: T11 | B12: P03 | C12: Map HR processes | D12: Planning | E12: 90 | F12: 100 | G12: Done | H12: R06
A13: T12 | B13: P03 | C13: Build portal | D13: Execution | E13: 320 | F13: 365 | G13: Done | H13: R08
... A32: T31 | B32: P08 | C32: Finance team rollout | D32: Closing | E32: 50 | F32: 48 | G32: Done | H32: R04

Sheet Resources
A1: Resource ID | B1: Name | C1: Role | D1: Department | E1: Hourly Rate
A2: R01 | B2: Aisha Khan | C2: Project Manager | D2: PMO | E2: 85
A3: R02 | B3: Daniel Wong | C3: Project Manager | D3: PMO | E3: 90
A4: R03 | B4: Maria Lopez | C4: Project Manager | D4: PMO | E4: 80
A5: R04 | B5: Priya Patel | C5: Project Manager | D5: PMO | E5: 82
A6: R05 | B6: Tom Becker | C6: Project Coordinator | D6: Facilities | E6: 55
A7: R06 | B7: Leila Haddad | C7: Business Analyst | D7: IT | E7: 70
A8: R07 | B8: Jonas Meyer | C8: Data Engineer | D8: IT | E8: 78
A9: R08 | B9: Grace Kim | C9: Developer | D9: IT | E9: 75
A10: R09 | B10: Omar Siddiqui | C10: QA Analyst | D10: IT | E10: 62
A11: R10 | B11: Chloe Martin | C11: Data Analyst | D11: Marketing | E11: 68

Sheet Risks
A1: Risk ID | B1: Project ID | C1: Description | D1: Probability | E1: Impact Cost | F1: Status | G1: Owner ID
A2: K01 | B2: P01 | C2: Data quality issues delay migration | D2: 0.6 | E2: 40000 | F2: Open | G2: R07
A3: K02 | B3: P01 | C3: Sales team resists new CRM | D3: 0.4 | E3: 25000 | F3: Open | G3: R01
A4: K03 | B4: P02 | C4: Source system access delayed | D4: 0.5 | E4: 60000 | F4: Open | G4: R02
A5: K04 | B5: P02 | C5: ETL performance below target | D5: 0.3 | E5: 45000 | F5: Open | G5: R07
A6: K05 | B6: P03 | C6: Payroll integration defects | D6: 0.2 | E6: 15000 | F6: Closed | G6: R08
A7: K06 | B7: P04 | C7: Conveyor delivery delayed by supplier | D7: 0.7 | E7: 150000 | F7: Open | G7: R02
A8: K07 | B8: P04 | C8: Software integration vendor unavailable | D8: 0.5 | E8: 90000 | F8: Open | G8: R08
A9: K08 | B9: P05 | C9: Low survey response rate | D9: 0.4 | E9: 10000 | F9: Open | G9: R10
A10: K09 | B10: P06 | C10: Lease signing delayed | D10: 0.3 | E10: 50000 | F10: Closed | G10: R05
A11: K10 | B11: P06 | C11: Furniture supplier backorder | D11: 0.6 | E11: 35000 | F11: Open | G11: R05
A12: K11 | B12: P07 | C12: Low training attendance | D12: 0.5 | E12: 8000 | F12: Open | G12: R01
A13: K12 | B13: P08 | C13: Finance users reject new tool | D13: 0.2 | E13: 12000 | F13: Closed | G13: R04

Sheet Exercises
A1: # | B1: Exercise | C1: Sheet | D1: Cell | E1: Fill down to | F1: Instructions
A2: 1 | B2: Earned value (EV) | C2: Projects | D2: L2 | E2: row 9 | F2: In L2, calculate Earned Value for the first project: EV = Budget × % Complete. Your formula must still work when filled down to row 9.
A3: 2 | B3: Planned value (PV) | C3: Projects | D3: M2 | E3: row 9 | F3: In M2, calculate Planned Value: PV = Budget × Planned %. It must work when filled down.
A4: 3 | B4: Cost variance (CV) | C4: Projects | D4: N2 | E4: row 9 | F4: In N2, calculate Cost Variance: CV = EV − AC. Calculate EV inside the formula (do not refer to L2). Negative means over budget.
A5: 4 | B5: CPI with IFERROR | C5: Projects | D5: O2 | E5: row 9 | F5: In O2, calculate the Cost Performance Index: CPI = EV ÷ AC. One project has no cost yet, which causes a #DIV/0! error. Wrap the formula so it shows 0 instead.
A6: 5 | B6: Schedule performance (SPI) | C6: Projects | D6: P2 | E6: row 9 | F6: In P2, calculate SPI = EV ÷ PV, which simplifies to % Complete ÷ Planned %. If Planned % is 0, show 1.
A7: 6 | B7: RAG status | C7: Projects | D7: Q2 | E7: row 9 | F7: In Q2, return a RAG status from SPI: "Green" if Planned % is 0 or SPI ≥ 0.95, "Amber" if SPI ≥ 0.85, otherwise "Red".
A8: 7 | B8: Budget check | C8: Projects | D8: R2 | E8: row 9 | F8: In R2, show "Over budget" when Actual Cost is greater than Budget, otherwise "Within budget".
A9: 8 | B9: Manager name lookup | C9: Projects | D9: S2 | E9: row 9 | F9: In S2, look up the manager's name from the Resources sheet (Resources!A2:E11) using the Manager ID in D2. Lock the lookup range with $ so it does not move when filled down.
A10: 9 | B10: Total budget | C10: Projects | D10: G11 | F10: In G11, add up the budgets of all eight projects (G2 to G9).
A11: 10 | B11: Total actual cost | C11: Projects | D11: H11 | F11: In H11, add up the actual cost of all projects.
A12: 11 | B12: Average % complete | C12: Projects | D12: I11 | F12: In I11, calculate the average % complete across the projects.
A13: 12 | B13: Count in-progress projects | C13: Projects | D13: B13 | F13: In B13, count how many projects have the status "In Progress".
A14: 13 | B14: Budget of high-priority projects | C14: Projects | D14: B14 | F14: In B14, add up the budget of projects whose priority is "High".
A15: 14 | B15: Portfolio CPI | C15: Projects | D15: B15 | F15: In B15, calculate the CPI of the whole portfolio: total EV ÷ total AC. Total EV is the sum of Budget × % Complete for every project, in one formula.
A16: 15 | B16: Blocked tasks | C16: Projects | D16: B16 | F16: In B16, count the tasks on the Tasks sheet with status "Blocked" (Tasks!G2:G32).
A17: 16 | B17: Planned hours for one project | C17: Projects | D17: B17 | F17: In B17, add up the planned hours (Tasks!E2:E32) of all tasks for project "P04" (Tasks!B2:B32).
A18: 17 | B18: Done tasks in a project | C18: Projects | D18: B18 | F18: In B18, count tasks that belong to project "P01" and have status "Done".
A19: 18 | B19: Project with the largest budget | C19: Projects | D19: B19 | F19: In B19, return the name of the project with the largest budget, using INDEX and MATCH (no typing the name).
A20: 19 | B20: Hours variance % | C20: Tasks | D20: I2 | E20: row 32 | F20: On the Tasks sheet, in I2, calculate the hours variance as a fraction: (Actual Hours − Planned Hours) ÷ Planned Hours. It must work when filled down to row 32.
A21: 20 | B21: Labour cost per task | C21: Tasks | D21: J2 | E21: row 32 | F21: On the Tasks sheet, in J2, calculate labour cost: Actual Hours × the owner's hourly rate, looked up from Resources (rate is column 5 of Resources!A2:E11).

Sheet Answers
A1: # | B1: Exercise | C1: Cell | D1: Model formula (type = first)
A2: 1 | B2: Earned value (EV) | C2: Projects!L2 | D2: G2*I2
A3: 2 | B3: Planned value (PV) | C3: Projects!M2 | D3: G2*J2
A4: 3 | B4: Cost variance (CV) | C4: Projects!N2 | D4: G2*I2-H2
A5: 4 | B5: CPI with IFERROR | C5: Projects!O2 | D5: IFERROR(G2*I2/H2,0)
A6: 5 | B6: Schedule performance (SPI) | C6: Projects!P2 | D6: IF(J2=0,1,I2/J2)
A7: 6 | B7: RAG status | C7: Projects!Q2 | D7: IF(J2=0,"Green",IF(I2/J2>=0.95,"Green",IF(I2/J2>=0.85,"Amber","Red")))
A8: 7 | B8: Budget check | C8: Projects!R2 | D8: IF(H2>G2,"Over budget","Within budget")
A9: 8 | B9: Manager name lookup | C9: Projects!S2 | D9: VLOOKUP(D2,Resources!$A$2:$E$11,2,FALSE)
A10: 9 | B10: Total budget | C10: Projects!G11 | D10: SUM(G2:G9)
A11: 10 | B11: Total actual cost | C11: Projects!H11 | D11: SUM(H2:H9)
A12: 11 | B12: Average % complete | C12: Projects!I11 | D12: AVERAGE(I2:I9)
A13: 12 | B13: Count in-progress projects | C13: Projects!B13 | D13: COUNTIF(E2:E9,"In Progress")
... A21: 20 | B21: Labour cost per task | C21: Tasks!J2 | D21: F2*VLOOKUP(H2,Resources!$A$2:$E$11,5,FALSE)
A23: Formulas are shown without the leading = so you can read them. Type = and then the formula. Live versions are on the "(solved)" sheets.

Sheet Projects (solved)
A1: Project ID | B1: Project | C1: Department | D1: Manager ID | E1: Status | F1: Priority | G1: Budget (BAC) | H1: Actual Cost (AC) | I1: % Complete | J1: Planned % | L1: EV | M1: PV | N1: CV | O1: CPI | P1: SPI | Q1: RAG | R1: Budget check | S1: Manager
A2: P01 | B2: CRM Upgrade | C2: IT | D2: R01 | E2: In Progress | F2: High | G2: 250000 | H2: 182000 | I2: 0.68 | J2: 0.75 | L2: =G2*I2 -> 170000 | M2: =G2*J2 -> 187500 | N2: =G2*I2-H2 -> -12000 | O2: =IFERROR(G2*I2/H2,0) -> 0.93406593 | P2: =IF(J2=0,1,I2/J2) -> 0.90666667 | Q2: =IF(J2=0,"Green",IF(I2/J2>=0.95,"Green",IF(I2/J2>=0.85,"Amber","Red"))) -> Amber | R2: =IF(H2>G2,"Over budget","Within budget") -> Within budget | S2: =VLOOKUP(D2,Resources!$A$2:$E$11,2,FALSE()) -> Aisha Khan
A3: P02 | B3: Data Warehouse Migration | C3: IT | D3: R02 | E3: In Progress | F3: High | G3: 480000 | H3: 265000 | I3: 0.52 | J3: 0.55 | L3: =G3*I3 -> 249600 | M3: =G3*J3 -> 264000 | N3: =G3*I3-H3 -> -15400 | O3: =IFERROR(G3*I3/H3,0) -> 0.94188679 | P3: =IF(J3=0,1,I3/J3) -> 0.94545455 | Q3: =IF(J3=0,"Green",IF(I3/J3>=0.95,"Green",IF(I3/J3>=0.85,"Amber","Red"))) -> Amber | R3: =IF(H3>G3,"Over budget","Within budget") -> Within budget | S3: =VLOOKUP(D3,Resources!$A$2:$E$11,2,FALSE()) -> Daniel Wong
A4: P03 | B4: HR Self-Service Portal | C4: HR | D4: R03 | E4: Completed | F4: Medium | G4: 120000 | H4: 128500 | I4: 1 | J4: 1 | L4: =G4*I4 -> 120000 | M4: =G4*J4 -> 120000 | N4: =G4*I4-H4 -> -8500 | O4: =IFERROR(G4*I4/H4,0) -> 0.93385214 | P4: =IF(J4=0,1,I4/J4) -> 1 | Q4: =IF(J4=0,"Green",IF(I4/J4>=0.95,"Green",IF(I4/J4>=0.85,"Amber","Red"))) -> Green | R4: =IF(H4>G4,"Over budget","Within budget") -> Over budget | S4: =VLOOKUP(D4,Resources!$A$2:$E$11,2,FALSE()) -> Maria Lopez
A5: P04 | B5: Warehouse Automation | C5: Operations | D5: R02 | E5: In Progress | F5: High | G5: 900000 | H5: 410000 | I5: 0.4 | J5: 0.48 | L5: =G5*I5 -> 360000 | M5: =G5*J5 -> 432000 | N5: =G5*I5-H5 -> -50000 | O5: =IFERROR(G5*I5/H5,0) -> 0.87804878 | P5: =IF(J5=0,1,I5/J5) -> 0.83333333 | Q5: =IF(J5=0,"Green",IF(I5/J5>=0.95,"Green",IF(I5/J5>=0.85,"Amber","Red"))) -> Red | R5: =IF(H5>G5,"Over budget","Within budget") -> Within budget | S5: =VLOOKUP(D5,Resources!$A$2:$E$11,2,FALSE()) -> Daniel Wong
A6: P05 | B6: Customer Feedback Analytics | C6: Marketing | D6: R04 | E6: In Progress | F6: Medium | G6: 95000 | H6: 61000 | I6: 0.7 | J6: 0.65 | L6: =G6*I6 -> 66500 | M6: =G6*J6 -> 61750 | N6: =G6*I6-H6 -> 5500 | O6: =IFERROR(G6*I6/H6,0) -> 1.0901639 | P6: =IF(J6=0,1,I6/J6) -> 1.0769231 | Q6: =IF(J6=0,"Green",IF(I6/J6>=0.95,"Green",IF(I6/J6>=0.85,"Amber","Red"))) -> Green | R6: =IF(H6>G6,"Over budget","Within budget") -> Within budget | S6: =VLOOKUP(D6,Resources!$A$2:$E$11,2,FALSE()) -> Priya Patel
A7: P06 | B7: Office Relocation | C7: Facilities | D7: R05 | E7: At Risk | F7: Medium | G7: 210000 | H7: 150000 | I7: 0.55 | J7: 0.7 | L7: =G7*I7 -> 115500 | M7: =G7*J7 -> 147000 | N7: =G7*I7-H7 -> -34500 | O7: =IFERROR(G7*I7/H7,0) -> 0.77 | P7: =IF(J7=0,1,I7/J7) -> 0.78571429 | Q7: =IF(J7=0,"Green",IF(I7/J7>=0.95,"Green",IF(I7/J7>=0.85,"Amber","Red"))) -> Red | R7: =IF(H7>G7,"Over budget","Within budget") -> Within budget | S7: =VLOOKUP(D7,Resources!$A$2:$E$11,2,FALSE()) -> Tom Becker
A8: P07 | B8: Cybersecurity Training | C8: IT | D8: R01 | E8: Not Started | F8: Low | G8: 60000 | H8: 0 | I8: 0 | J8: 0.1 | L8: =G8*I8 -> 0 | M8: =G8*J8 -> 6000 | N8: =G8*I8-H8 -> 0 | O8: =IFERROR(G8*I8/H8,0) -> 0 | P8: =IF(J8=0,1,I8/J8) -> 0 | Q8: =IF(J8=0,"Green",IF(I8/J8>=0.95,"Green",IF(I8/J8>=0.85,"Amber","Red"))) -> Red | R8: =IF(H8>G8,"Over budget","Within budget") -> Within budget | S8: =VLOOKUP(D8,Resources!$A$2:$E$11,2,FALSE()) -> Aisha Khan
A9: P08 | B9: Budget Planning Tool | C9: Finance | D9: R04 | E9: Completed | F9: Low | G9: 75000 | H9: 71200 | I9: 1 | J9: 1 | L9: =G9*I9 -> 75000 | M9: =G9*J9 -> 75000 | N9: =G9*I9-H9 -> 3800 | O9: =IFERROR(G9*I9/H9,0) -> 1.0533708 | P9: =IF(J9=0,1,I9/J9) -> 1 | Q9: =IF(J9=0,"Green",IF(I9/J9>=0.95,"Green",IF(I9/J9>=0.85,"Amber","Red"))) -> Green | R9: =IF(H9>G9,"Over budget","Within budget") -> Within budget | S9: =VLOOKUP(D9,Resources!$A$2:$E$11,2,FALSE()) -> Priya Patel
A11: Total | G11: =SUM(G2:G9) -> 2190000 | H11: =SUM(H2:H9) -> 1267700 | I11: =AVERAGE(I2:I9) -> 0.60625
A13: In-progress projects | B13: =COUNTIF(E2:E9,"In Progress") -> 4
A14: High-priority budget | B14: =SUMIF(F2:F9,"High",G2:G9) -> 1630000
A15: Portfolio CPI | B15: =SUMPRODUCT(G2:G9,I2:I9)/SUM(H2:H9) -> 0.91236097
A16: Blocked tasks | B16: =COUNTIF(Tasks!G2:G32,"Blocked") -> 2
A17: P04 planned hours | B17: =SUMIFS(Tasks!E2:E32,Tasks!B2:B32,"P04") -> 1670
A18: P01 tasks done | B18: =COUNTIFS(Tasks!B2:B32,"P01",Tasks!G2:G32,"Done") -> 2
A19: Largest project | B19: =INDEX(B2:B9,MATCH(MAX(G2:G9),G2:G9,0)) -> Warehouse Automation

Sheet Tasks (solved)
A1: Task ID | B1: Project ID | C1: Task | D1: Phase | E1: Planned Hours | F1: Actual Hours | G1: Status | H1: Owner ID | I1: Hours variance % | J1: Labour cost
A2: T01 | B2: P01 | C2: Gather CRM requirements | D2: Planning | E2: 120 | F2: 135 | G2: Done | H2: R06 | I2: =(F2-E2)/E2 -> 0.125 | J2: =F2*VLOOKUP(H2,Resources!$A$2:$E$11,5,FALSE()) -> 9450
A3: T02 | B3: P01 | C3: Configure CRM modules | D3: Execution | E3: 400 | F3: 380 | G3: Done | H3: R08 | I3: =(F3-E3)/E3 -> -0.05 | J3: =F3*VLOOKUP(H3,Resources!$A$2:$E$11,5,FALSE()) -> 28500
A4: T03 | B4: P01 | C4: Migrate customer data | D4: Execution | E4: 240 | F4: 210 | G4: In Progress | H4: R07 | I4: =(F4-E4)/E4 -> -0.125 | J4: =F4*VLOOKUP(H4,Resources!$A$2:$E$11,5,FALSE()) -> 16380
A5: T04 | B5: P01 | C5: User acceptance testing | D5: Testing | E5: 160 | F5: 60 | G5: In Progress | H5: R09 | I5: =(F5-E5)/E5 -> -0.625 | J5: =F5*VLOOKUP(H5,Resources!$A$2:$E$11,5,FALSE()) -> 3720
A6: T05 | B6: P01 | C6: Train sales team | D6: Closing | E6: 80 | F6: 0 | G6: Not Started | H6: R01 | I6: =(F6-E6)/E6 -> -1 | J6: =F6*VLOOKUP(H6,Resources!$A$2:$E$11,5,FALSE()) -> 0
A7: T06 | B7: P02 | C7: Assess source systems | D7: Planning | E7: 150 | F7: 170 | G7: Done | H7: R06 | I7: =(F7-E7)/E7 -> 0.13333333 | J7: =F7*VLOOKUP(H7,Resources!$A$2:$E$11,5,FALSE()) -> 11900
A8: T07 | B8: P02 | C8: Design warehouse model | D8: Planning | E8: 200 | F8: 230 | G8: Done | H8: R07 | I8: =(F8-E8)/E8 -> 0.15 | J8: =F8*VLOOKUP(H8,Resources!$A$2:$E$11,5,FALSE()) -> 17940
A9: T08 | B9: P02 | C9: Build ETL pipelines | D9: Execution | E9: 600 | F9: 340 | G9: In Progress | H9: R07 | I9: =(F9-E9)/E9 -> -0.43333333 | J9: =F9*VLOOKUP(H9,Resources!$A$2:$E$11,5,FALSE()) -> 26520
A10: T09 | B10: P02 | C10: Build Power BI reports | D10: Execution | E10: 300 | F10: 40 | G10: In Progress | H10: R10 | I10: =(F10-E10)/E10 -> -0.86666667 | J10: =F10*VLOOKUP(H10,Resources!$A$2:$E$11,5,FALSE()) -> 2720
A11: T10 | B11: P02 | C11: Data validation | D11: Testing | E11: 180 | F11: 0 | G11: Not Started | H11: R09 | I11: =(F11-E11)/E11 -> -1 | J11: =F11*VLOOKUP(H11,Resources!$A$2:$E$11,5,FALSE()) -> 0
A12: T11 | B12: P03 | C12: Map HR processes | D12: Planning | E12: 90 | F12: 100 | G12: Done | H12: R06 | I12: =(F12-E12)/E12 -> 0.11111111 | J12: =F12*VLOOKUP(H12,Resources!$A$2:$E$11,5,FALSE()) -> 7000
A13: T12 | B13: P03 | C13: Build portal | D13: Execution | E13: 320 | F13: 365 | G13: Done | H13: R08 | I13: =(F13-E13)/E13 -> 0.140625 | J13: =F13*VLOOKUP(H13,Resources!$A$2:$E$11,5,FALSE()) -> 27375
... A32: T31 | B32: P08 | C32: Finance team rollout | D32: Closing | E32: 50 | F32: 48 | G32: Done | H32: R04 | I32: =(F32-E32)/E32 -> -0.04 | J32: =F32*VLOOKUP(H32,Resources!$A$2:$E$11,5,FALSE()) -> 3936
